generic_map_api/VERSION
generic_map_api/__init__.py
generic_map_api/bounding_box.py
generic_map_api/caching.py
generic_map_api/clustering.py
generic_map_api/constants.py
generic_map_api/date_line_normalization.py
generic_map_api/geometry_serializers.py
generic_map_api/params.py
generic_map_api/routers.py
generic_map_api/serializers.py
generic_map_api/utils.py
generic_map_api/values.py
generic_map_api/views.py
generic_map_api/multi_meta/__init__.py
generic_map_api/multi_meta/urls.py
generic_map_api/multi_meta/views.py
generic_map_api/resources/empty_tile.jpeg
generic_map_api/resources/empty_tile.png
generic_map_api/resources/empty_tile.webp
generic_map_api/resources/icons/default-features.png
generic_map_api/resources/icons/default-tiles.png
generic_map_api/resources/icons/default.png
skytek_generic_map_api-0.12.1.dist-info/LICENSE
skytek_generic_map_api-0.12.1.dist-info/METADATA
skytek_generic_map_api-0.12.1.dist-info/WHEEL
skytek_generic_map_api-0.12.1.dist-info/top_level.txt
skytek_generic_map_api-0.12.1.dist-info/RECORD
