Metadata-Version: 2.1
Name: skytek-generic-map-api
Version: 0.12.1
Summary: skytek-generic-map-api - expose geographical data for Skytek's frontends
Home-page: http://github.com/Skytek/generic-map-api
Author: Skytek Ltd.
Author-email: wiktor.latanowicz@skytek.com
License: LGPLv3
Classifier: Programming Language :: Python :: 3.10
Classifier: License :: OSI Approved :: GNU Lesser General Public License v3 (LGPLv3)
Classifier: Operating System :: OS Independent
Classifier: Topic :: Scientific/Engineering :: GIS
Requires-Python: >=3.10
License-File: LICENSE
Requires-Dist: djangorestframework >=3.14.0
Requires-Dist: shapely >=1.8.4
Requires-Dist: scikit-learn >=1.1.2
Requires-Dist: geohash2 >=1.1
Requires-Dist: python-dateutil >=2.8.1
Requires-Dist: skytek-utils >=0.9.0
